[
    [
        {
            "serialNumber": "dummy_chip1",
            "testType": "INJECTION_CAPACITANCE",
            "subtestType": "",
            "results": {
                "property": {
                    "YARR_VERSION": "emulator",
                    "INJECTION_CAPACITANCE_MEASUREMENT_VERSION": "2.2.7"
                },
                "comment": "",
                "Measurements": {
                    "Vmux4": {
                        "X": false,
                        "Unit": "V",
                        "Values": [
                            1.5479120971119267,
                            0.4544774435695538,
                            1.4895243118156343,
                            1.6095287149936037,
                            1.3368059235809433
                        ]
                    },
                    "Vmux30": {
                        "X": false,
                        "Unit": "V",
                        "Values": [
                            0.0,
                            0.0,
                            0.0,
                            0.0,
                            0.0
                        ]
                    },
                    "Imux10": {
                        "X": false,
                        "Unit": "V",
                        "Values": [
                            1.9512447032735118,
                            1.5161754801707477,
                            0.3789427181685714,
                            0.39981640495021664,
                            1.1071588013159916
                        ]
                    },
                    "Imux11": {
                        "X": false,
                        "Unit": "V",
                        "Values": [
                            0.7415960484651625,
                            0.38927741570393515,
                            0.8743038377446615,
                            1.5614580620439358,
                            0.4291693456390584
                        ]
                    },
                    "Imux63": {
                        "X": false,
                        "Unit": "V",
                        "Values": [
                            0.0,
                            0.0,
                            0.0,
                            0.0,
                            0.0
                        ]
                    }
                },
                "Metadata": {
                    "FirmwareVersion": "",
                    "FirmwareIdentifier": "",
                    "ChannelConfig": "",
                    "SoftwareVersion": "",
                    "ChipConfigs": {
                        "RD53B": {
                            "GlobalConfig": {
                                "AuroraActiveLanes": 1,
                                "CmlBias0": 500,
                                "CmlBias1": 100,
                                "CmlBias2": 0,
                                "ServiceBlockEn": 1,
                                "DiffPreComp": 350,
                                "DiffPreampL": 500,
                                "DiffPreampM": 500,
                                "DiffPreampR": 500,
                                "DiffPreampT": 500,
                                "DiffPreampTL": 500,
                                "DiffPreampTR": 500,
                                "EnCoreCol0": 65535,
                                "EnCoreCol1": 65535,
                                "EnCoreCol2": 65535,
                                "EnCoreCol3": 63,
                                "DataMergeOutMux0": 2,
                                "DataMergeOutMux1": 3,
                                "DataMergeOutMux2": 0,
                                "DataMergeOutMux3": 1,
                                "MonitorI": 63,
                                "MonitorV": 1,
                                "SerEnLane": 4,
                                "SldoTrimA": 3,
                                "SldoTrimD": 4
                            },
                            "Parameter": {
                                "ADCcalPar": [
                                    4.247,
                                    0.204,
                                    4990.0
                                ],
                                "Name": "dummy_chip1",
                                "ChipId": 12,
                                "InjCap": 8.09,
                                "NfDSLDO": 1.288113319545111,
                                "NfASLDO": 1.2729076673036923,
                                "NfACB": 1.2698521239148954,
                                "VcalPar": [
                                    5.36,
                                    0.216
                                ],
                                "IrefTrim": 10,
                                "KSenseInA": 21326.065,
                                "KSenseInD": 21248.092,
                                "KSenseShuntA": 26403.699523809522,
                                "KSenseShuntD": 26307.161523809526,
                                "KShuntA": 1092.985,
                                "KShuntD": 1085.872
                            }
                        }
                    },
                    "SoftwareType": "",
                    "ChipID": 12,
                    "Name": "dummy_chip1",
                    "Institution": "TEST",
                    "ModuleSN": "20UPGXM1234567",
                    "TimeStart": 1727989610,
                    "TimeEnd": 1727989616
                }
            }
        }
    ],
    [
        {
            "serialNumber": "dummy_chip3",
            "testType": "INJECTION_CAPACITANCE",
            "subtestType": "",
            "results": {
                "property": {
                    "YARR_VERSION": "emulator",
                    "INJECTION_CAPACITANCE_MEASUREMENT_VERSION": "2.2.7"
                },
                "comment": "",
                "Measurements": {
                    "Vmux4": {
                        "X": false,
                        "Unit": "V",
                        "Values": [
                            0.8777568795041046,
                            1.1091695740316696,
                            1.93501946486842,
                            0.7749567580603489,
                            0.942192412286265
                        ]
                    },
                    "Vmux30": {
                        "X": false,
                        "Unit": "V",
                        "Values": [
                            0.0,
                            0.0,
                            0.0,
                            0.0,
                            0.0
                        ]
                    },
                    "Imux10": {
                        "X": false,
                        "Unit": "V",
                        "Values": [
                            1.522279403980706,
                            0.7090519362597367,
                            0.2598430106709433,
                            0.014724539502011025,
                            1.118414321490827
                        ]
                    },
                    "Imux11": {
                        "X": false,
                        "Unit": "V",
                        "Values": [
                            1.8535299776972036,
                            0.9334420074540684,
                            1.6653563921156749,
                            0.9178315510766799,
                            0.8170572874492723
                        ]
                    },
                    "Imux63": {
                        "X": false,
                        "Unit": "V",
                        "Values": [
                            0.0,
                            0.0,
                            0.0,
                            0.0,
                            0.0
                        ]
                    }
                },
                "Metadata": {
                    "FirmwareVersion": "",
                    "FirmwareIdentifier": "",
                    "ChannelConfig": "",
                    "SoftwareVersion": "",
                    "ChipConfigs": {
                        "RD53B": {
                            "GlobalConfig": {
                                "AuroraActiveLanes": 1,
                                "CmlBias0": 500,
                                "CmlBias1": 100,
                                "CmlBias2": 0,
                                "ServiceBlockEn": 1,
                                "DiffPreComp": 350,
                                "DiffPreampL": 500,
                                "DiffPreampM": 500,
                                "DiffPreampR": 500,
                                "DiffPreampT": 500,
                                "DiffPreampTL": 500,
                                "DiffPreampTR": 500,
                                "EnCoreCol0": 65535,
                                "EnCoreCol1": 65535,
                                "EnCoreCol2": 65535,
                                "EnCoreCol3": 65535,
                                "DataMergeOutMux0": 1,
                                "DataMergeOutMux1": 2,
                                "DataMergeOutMux2": 3,
                                "DataMergeOutMux3": 0,
                                "MonitorI": 63,
                                "MonitorV": 1,
                                "SerEnLane": 8,
                                "SldoTrimA": 12,
                                "SldoTrimD": 8
                            },
                            "Parameter": {
                                "ADCcalPar": [
                                    16.892,
                                    0.193,
                                    4990.0
                                ],
                                "Name": "dummy_chip3",
                                "ChipId": 14,
                                "InjCap": 7.929000000000001,
                                "NfDSLDO": 1.2899371430024733,
                                "NfASLDO": 1.2851400704055398,
                                "NfACB": 1.2810776846027314,
                                "VcalPar": [
                                    3.056,
                                    0.206
                                ],
                                "IrefTrim": 12,
                                "KSenseInA": 21431.85,
                                "KSenseInD": 21441.496,
                                "KSenseShuntA": 26534.67142857143,
                                "KSenseShuntD": 26546.614095238096,
                                "KShuntA": 1092.985,
                                "KShuntD": 1085.872
                            }
                        }
                    },
                    "SoftwareType": "",
                    "ChipID": 14,
                    "Name": "dummy_chip3",
                    "Institution": "TEST",
                    "ModuleSN": "20UPGXM1234567",
                    "TimeStart": 1727989610,
                    "TimeEnd": 1727989616
                }
            }
        }
    ],
    [
        {
            "serialNumber": "dummy_chip4",
            "testType": "INJECTION_CAPACITANCE",
            "subtestType": "",
            "results": {
                "property": {
                    "YARR_VERSION": "emulator",
                    "INJECTION_CAPACITANCE_MEASUREMENT_VERSION": "2.2.7"
                },
                "comment": "",
                "Measurements": {
                    "Vmux4": {
                        "X": false,
                        "Unit": "V",
                        "Values": [
                            1.717195839822765,
                            0.12763451220835065,
                            0.6516507162763039,
                            0.5766562078604882,
                            1.1304722129623777
                        ]
                    },
                    "Vmux30": {
                        "X": false,
                        "Unit": "V",
                        "Values": [
                            0.0,
                            0.0,
                            0.0,
                            0.0,
                            0.0
                        ]
                    },
                    "Imux10": {
                        "X": false,
                        "Unit": "V",
                        "Values": [
                            1.5721286105539076,
                            1.9413960487898065,
                            0.9514098524518675,
                            1.5738487550042768,
                            0.6079001961252244
                        ]
                    },
                    "Imux11": {
                        "X": false,
                        "Unit": "V",
                        "Values": [
                            1.287730240161329,
                            0.08760753157445755,
                            1.4005302040044982,
                            1.1374823919057875,
                            1.7068061465363322
                        ]
                    },
                    "Imux63": {
                        "X": false,
                        "Unit": "V",
                        "Values": [
                            0.0,
                            0.0,
                            0.0,
                            0.0,
                            0.0
                        ]
                    }
                },
                "Metadata": {
                    "FirmwareVersion": "",
                    "FirmwareIdentifier": "",
                    "ChannelConfig": "",
                    "SoftwareVersion": "",
                    "ChipConfigs": {
                        "RD53B": {
                            "GlobalConfig": {
                                "AuroraActiveLanes": 1,
                                "CmlBias0": 500,
                                "CmlBias1": 100,
                                "CmlBias2": 0,
                                "ServiceBlockEn": 1,
                                "DiffPreComp": 350,
                                "DiffPreampL": 500,
                                "DiffPreampM": 500,
                                "DiffPreampR": 500,
                                "DiffPreampT": 500,
                                "DiffPreampTL": 500,
                                "DiffPreampTR": 500,
                                "EnCoreCol0": 65535,
                                "EnCoreCol1": 65535,
                                "EnCoreCol2": 65535,
                                "EnCoreCol3": 63,
                                "DataMergeOutMux0": 0,
                                "DataMergeOutMux1": 1,
                                "DataMergeOutMux2": 2,
                                "DataMergeOutMux3": 3,
                                "MonitorI": 63,
                                "MonitorV": 1,
                                "SerEnLane": 1,
                                "SldoTrimA": 8,
                                "SldoTrimD": 5
                            },
                            "Parameter": {
                                "ADCcalPar": [
                                    10.352,
                                    0.198,
                                    4990.0
                                ],
                                "Name": "dummy_chip4",
                                "ChipId": 15,
                                "InjCap": 7.994,
                                "NfDSLDO": 1.280846634029738,
                                "NfASLDO": 1.2967912615564348,
                                "NfACB": 1.305268152140248,
                                "VcalPar": [
                                    5.122,
                                    0.211
                                ],
                                "IrefTrim": 10,
                                "KSenseInA": 21263.868,
                                "KSenseInD": 21459.463,
                                "KSenseShuntA": 26326.693714285713,
                                "KSenseShuntD": 26568.858952380953,
                                "KShuntA": 1092.985,
                                "KShuntD": 1085.872
                            }
                        }
                    },
                    "SoftwareType": "",
                    "ChipID": 15,
                    "Name": "dummy_chip4",
                    "Institution": "TEST",
                    "ModuleSN": "20UPGXM1234567",
                    "TimeStart": 1727989610,
                    "TimeEnd": 1727989616
                }
            }
        }
    ]
]